{
    "entites_geographiques": [
        {
            "entite": "Parc du château de Versailles",
            "type": "parc"
        },
        {
            "entite": "Jardins du château de Versailles",
            "type": "jardins"
        },
        {
            "entite": "Château de Versailles",
            "type": "château"
        },
        {
            "entite": "Versailles",
            "type": "ville"
        },
        {
            "entite": "Yvelines",
            "type": "département"
        },
        {
            "entite": "France",
            "type": "pays"
        }
    ]
}